flager/__init__.py
flager/exceptions.py
flager/main.py
flager/py.typed
flager-0.1.2.dist-info/LICENSE
flager-0.1.2.dist-info/METADATA
flager-0.1.2.dist-info/WHEEL
flager-0.1.2.dist-info/RECORD
