Metadata-Version: 2.1
Name: flager
Version: 0.1.2
Summary: 
Home-page: https://github.com/daxartio/flager
License: MIT
Author: Danil Akhtarov
Author-email: daxartio@gmail.com
Requires-Python: >=3.8,<4.0
Classifier: License :: OSI Approved :: MIT License
Classifier: Programming Language :: Python :: 3
Classifier: Programming Language :: Python :: 3.8
Classifier: Programming Language :: Python :: 3.9
Classifier: Programming Language :: Python :: 3.10
Classifier: Programming Language :: Python :: 3.11
Requires-Dist: anyio (>=4.0.0,<5.0.0)
Project-URL: Changelog, https://github.com/daxartio/flager/blob/main/CHANGELOG.md/
Project-URL: Repository, https://github.com/daxartio/flager
